dsperse/__init__.py
dsperse/deps_checker.py
dsperse/install.py
dsperse/main.py
dsperse/models/__init__.py
dsperse/models/doom/input.json
dsperse/models/doom/model.onnx
dsperse/models/net/input.json
dsperse/models/net/model.onnx
dsperse/src/__init__.py
dsperse/src/constants.py
dsperse/src/prover.py
dsperse/src/verifier.py
dsperse/src/analyzers/__init__.py
dsperse/src/analyzers/model_analyzer.py
dsperse/src/analyzers/onnx_analyzer.py
dsperse/src/analyzers/runner_analyzer.py
dsperse/src/backends/ezkl.py
dsperse/src/backends/jstprove.py
dsperse/src/backends/onnx_models.py
dsperse/src/backends/pth_models.py
dsperse/src/cli/__init__.py
dsperse/src/cli/base.py
dsperse/src/cli/compile.py
dsperse/src/cli/convert.py
dsperse/src/cli/full_run.py
dsperse/src/cli/prove.py
dsperse/src/cli/run.py
dsperse/src/cli/slice.py
dsperse/src/cli/verify.py
dsperse/src/compile/__init__.py
dsperse/src/compile/compiler.py
dsperse/src/compile/utils/compiler_utils.py
dsperse/src/run/__init__.py
dsperse/src/run/runner.py
dsperse/src/run/utils/__init__.py
dsperse/src/run/utils/runner_utils.py
dsperse/src/slice/__init__.py
dsperse/src/slice/onnx_slicer.py
dsperse/src/slice/slicer.py
dsperse/src/slice/utils/__init__.py
dsperse/src/slice/utils/converter.py
dsperse/src/slice/utils/onnx_utils.py
dsperse/src/slice/utils/torch_utils.py
dsperse/src/utils/__init__.py
dsperse/src/utils/srs_manager.py
dsperse/src/utils/torch_utils.py
dsperse/src/utils/utils.py
dsperse-2.0.dist-info/licenses/LICENSE
dsperse-2.0.dist-info/METADATA
dsperse-2.0.dist-info/WHEEL
dsperse-2.0.dist-info/entry_points.txt
dsperse-2.0.dist-info/top_level.txt
dsperse-2.0.dist-info/RECORD
