Metadata-Version: 2.4
Name: dsperse
Version: 2.0
Summary: Distributed zkML Toolkit
Author-email: Inference Labs <info@inferencelabs.com>
License: Copyright (c) 2025 Inference Labs Inc.
Requires-Python: ==3.12.*
License-File: LICENSE
Requires-Dist: torch==2.7.1
Requires-Dist: onnx==1.18.0
Requires-Dist: pytest>=8.4.1
Requires-Dist: ezkl==22.2.1
Requires-Dist: networkx~=3.4.2
Requires-Dist: matplotlib~=3.10.1
Requires-Dist: numpy~=2.2.3
Requires-Dist: tqdm~=4.67.1
Requires-Dist: onnxruntime==1.21.0
Requires-Dist: colorama~=0.4.6
Dynamic: license-file
